{ "compressionlevel":-1,
 "editorsettings":
    {
     "export":
        {
         "target":"."
        }
    },
 "height":29,
 "infinite":true,
 "layers":[
        {
         "chunks":[],
         "height":0,
         "id":1,
         "name":"start",
         "opacity":1,
         "startx":0,
         "starty":0,
         "type":"tilelayer",
         "visible":true,
         "width":0,
         "x":0,
         "y":0
        }, 
        {
         "chunks":[
                {
                 "data":[0, 0, 0, 0, 0, 0, 0, 0, 0, 0, 0, 0, 0, 0, 0, 0, 0, 0, 0, 0, 0, 0, 0, 0, 0, 0, 0, 0, 0, 0, 0, 0, 0, 0, 0, 0, 0, 0, 0, 0, 0, 0, 0, 0, 0, 0, 0, 0, 0, 0, 0, 0, 0, 0, 0, 0, 0, 0, 0, 0, 0, 0, 0, 0, 0, 0, 0, 0, 0, 0, 0, 0, 0, 0, 0, 0, 0, 0, 0, 0, 0, 0, 0, 0, 0, 0, 0, 0, 0, 0, 0, 0, 0, 0, 0, 0, 0, 0, 0, 0, 0, 0, 0, 0, 0, 0, 0, 0, 0, 0, 0, 0, 0, 0, 0, 0, 0, 0, 0, 0, 0, 0, 0, 0, 0, 0, 0, 0, 0, 0, 0, 0, 0, 0, 0, 0, 0, 0, 0, 0, 0, 0, 0, 0, 0, 0, 0, 0, 0, 0, 0, 0, 0, 0, 0, 0, 0, 0, 65, 0, 0, 0, 0, 0, 0, 0, 0, 0, 0, 0, 0, 0, 0, 0, 65, 0, 0, 0, 0, 0, 0, 0, 0, 0, 0, 0, 0, 0, 0, 0, 65, 0, 0, 0, 0, 0, 0, 0, 0, 0, 0, 0, 0, 0, 0, 0, 0, 0, 0, 0, 0, 0, 0, 0, 0, 0, 0, 0, 0, 0, 0, 0, 0, 0, 0, 0, 0, 0, 0, 0, 0, 0, 0, 0, 0, 0, 0, 0, 0, 0, 0, 0, 0, 0, 0, 0, 0, 0, 0, 0, 0, 0, 0, 0, 0, 0],
                 "height":16,
                 "width":16,
                 "x":0,
                 "y":0
                }],
         "height":16,
         "id":3,
         "name":"exit_WM",
         "opacity":1,
         "properties":[
                {
                 "name":"exitUrl",
                 "type":"string",
                 "value":"WM.json#start_WU"
                }],
         "startx":0,
         "starty":0,
         "type":"tilelayer",
         "visible":true,
         "width":16,
         "x":0,
         "y":0
        }, 
        {
         "chunks":[
                {
                 "data":[0, 0, 0, 0, 0, 0, 0, 0, 0, 0, 0, 0, 0, 0, 0, 0, 0, 0, 0, 0, 0, 0, 0, 0, 0, 0, 0, 0, 0, 0, 0, 0, 0, 0, 0, 0, 0, 0, 0, 0, 0, 0, 0, 0, 0, 0, 0, 0, 0, 0, 0, 0, 0, 0, 0, 0, 0, 0, 0, 0, 0, 0, 0, 0, 0, 0, 0, 0, 0, 0, 0, 0, 0, 0, 0, 0, 0, 0, 0, 0, 0, 0, 0, 0, 0, 0, 0, 0, 0, 0, 0, 0, 0, 0, 0, 0, 0, 0, 0, 0, 0, 0, 0, 0, 0, 0, 0, 0, 0, 0, 0, 0, 0, 0, 0, 0, 0, 0, 0, 0, 0, 0, 0, 0, 0, 0, 0, 0, 0, 0, 0, 0, 0, 0, 0, 0, 0, 0, 0, 0, 0, 0, 0, 0, 0, 0, 0, 0, 0, 0, 0, 0, 0, 0, 0, 0, 0, 0, 0, 66, 0, 0, 0, 0, 0, 0, 0, 0, 0, 0, 0, 0, 0, 0, 0, 66, 0, 0, 0, 0, 0, 0, 0, 0, 0, 0, 0, 0, 0, 0, 0, 66, 0, 0, 0, 0, 0, 0, 0, 0, 0, 0, 0, 0, 0, 0, 0, 0, 0, 0, 0, 0, 0, 0, 0, 0, 0, 0, 0, 0, 0, 0, 0, 0, 0, 0, 0, 0, 0, 0, 0, 0, 0, 0, 0, 0, 0, 0, 0, 0, 0, 0, 0, 0, 0, 0, 0, 0, 0, 0, 0, 0, 0, 0, 0, 0],
                 "height":16,
                 "width":16,
                 "x":0,
                 "y":0
                }],
         "height":16,
         "id":4,
         "name":"start_WM",
         "opacity":1,
         "properties":[
                {
                 "name":"startLayer",
                 "type":"bool",
                 "value":true
                }],
         "startx":0,
         "starty":0,
         "type":"tilelayer",
         "visible":true,
         "width":16,
         "x":0,
         "y":0
        }, 
        {
         "chunks":[
                {
                 "data":[0, 0, 0, 0, 0, 0, 0, 0, 0, 0, 0, 0, 0, 0, 0, 0, 0, 0, 0, 0, 0, 0, 0, 0, 0, 0, 0, 0, 0, 0, 0, 0, 0, 0, 0, 0, 0, 0, 0, 0, 0, 0, 0, 0, 0, 0, 0, 0, 0, 0, 0, 0, 0, 0, 0, 0, 0, 0, 0, 0, 0, 0, 0, 0, 0, 0, 0, 0, 0, 0, 0, 0, 0, 0, 0, 0, 0, 0, 0, 0, 0, 0, 0, 0, 0, 0, 0, 0, 0, 0, 0, 0, 0, 0, 0, 0, 0, 0, 0, 0, 0, 0, 0, 0, 0, 0, 0, 0, 0, 0, 0, 0, 0, 0, 0, 0, 0, 0, 0, 0, 0, 0, 0, 0, 0, 0, 0, 0, 0, 0, 0, 0, 0, 0, 0, 0, 0, 0, 0, 0, 0, 0, 0, 0, 0, 0, 0, 0, 0, 0, 0, 0, 0, 0, 0, 0, 0, 0, 0, 0, 0, 0, 0, 0, 0, 0, 0, 0, 0, 0, 0, 0, 0, 0, 0, 0, 0, 0, 0, 0, 0, 0, 0, 0, 0, 0, 0, 0, 0, 0, 0, 0, 0, 0, 0, 0, 0, 0, 0, 0, 0, 0, 0, 0, 0, 0, 0, 0, 0, 0, 0, 0, 0, 0, 0, 0, 0, 0, 0, 0, 0, 0, 0, 68, 0, 0, 0, 0, 0, 0, 0, 0, 0, 0, 0, 0, 0, 0, 68, 0, 0, 0, 0, 0, 0, 0, 0, 0, 0, 0, 0, 0, 0, 68, 0, 0],
                 "height":16,
                 "width":16,
                 "x":-16,
                 "y":-16
                }, 
                {
                 "data":[0, 0, 0, 0, 0, 0, 0, 0, 0, 0, 0, 0, 0, 0, 0, 0, 0, 0, 0, 0, 0, 0, 0, 0, 0, 0, 0, 0, 0, 0, 0, 0, 0, 0, 0, 0, 0, 0, 0, 0, 0, 0, 0, 0, 0, 0, 0, 0, 0, 0, 0, 0, 0, 0, 0, 0, 0, 0, 0, 0, 0, 0, 0, 0, 0, 0, 0, 0, 0, 0, 0, 0, 0, 0, 0, 0, 0, 0, 0, 0, 0, 0, 0, 0, 0, 0, 0, 0, 0, 0, 0, 0, 0, 0, 0, 0, 0, 0, 0, 0, 0, 0, 0, 0, 0, 0, 0, 0, 0, 0, 0, 0, 0, 0, 0, 0, 0, 0, 0, 0, 0, 0, 0, 0, 0, 0, 0, 0, 0, 0, 0, 0, 0, 0, 0, 0, 0, 0, 0, 0, 0, 0, 0, 0, 0, 0, 0, 0, 0, 0, 0, 0, 0, 0, 0, 0, 0, 0, 0, 0, 0, 0, 0, 0, 0, 0, 0, 68, 68, 68, 68, 68, 68, 0, 0, 0, 0, 0, 0, 0, 68, 68, 68, 0, 0, 0, 0, 0, 0, 68, 68, 68, 0, 68, 68, 68, 0, 0, 0, 0, 0, 0, 0, 0, 0, 0, 0, 0, 68, 0, 0, 0, 0, 0, 0, 0, 0, 0, 0, 0, 0, 0, 0, 0, 0, 0, 0, 0, 0, 0, 0, 0, 0, 0, 0, 0, 0, 0, 0, 0, 0, 0, 0, 0, 0, 0, 0, 0, 0, 0, 0, 0, 0, 0, 0, 0],
                 "height":16,
                 "width":16,
                 "x":0,
                 "y":-16
                }, 
                {
                 "data":[0, 0, 0, 0, 0, 0, 0, 0, 0, 0, 0, 0, 0, 0, 0, 0, 0, 0, 0, 0, 0, 0, 0, 0, 0, 0, 0, 0, 0, 0, 0, 0, 0, 0, 0, 0, 0, 0, 0, 0, 0, 0, 0, 0, 0, 0, 0, 0, 0, 0, 0, 0, 0, 0, 0, 0, 0, 0, 0, 0, 0, 0, 0, 0, 0, 0, 0, 0, 0, 0, 0, 0, 0, 0, 0, 0, 0, 0, 0, 0, 0, 0, 0, 0, 0, 0, 0, 0, 0, 0, 0, 0, 0, 0, 0, 0, 0, 0, 0, 0, 0, 0, 0, 0, 0, 0, 0, 0, 0, 0, 0, 0, 0, 0, 0, 0, 0, 0, 0, 0, 0, 0, 0, 0, 0, 0, 0, 0, 0, 0, 0, 0, 0, 0, 0, 0, 0, 0, 0, 0, 0, 0, 0, 0, 0, 0, 0, 0, 0, 0, 0, 0, 0, 0, 0, 0, 0, 0, 0, 0, 0, 0, 0, 0, 0, 0, 0, 0, 0, 0, 0, 0, 0, 0, 0, 0, 0, 0, 0, 0, 0, 0, 0, 0, 0, 0, 0, 0, 0, 0, 0, 0, 68, 68, 68, 0, 0, 0, 0, 0, 0, 0, 0, 0, 0, 0, 0, 0, 0, 0, 0, 68, 68, 0, 0, 0, 0, 0, 0, 0, 0, 0, 0, 0, 0, 0, 0, 0, 0, 68, 0, 0, 0, 0, 0, 0, 0, 0, 0, 0, 0, 0, 0, 0, 0, 0, 68, 0, 0, 0, 0, 0, 0, 0, 0, 0],
                 "height":16,
                 "width":16,
                 "x":16,
                 "y":-16
                }, 
                {
                 "data":[0, 0, 0, 0, 0, 0, 0, 0, 0, 0, 0, 0, 0, 68, 0, 0, 0, 0, 0, 0, 0, 0, 0, 0, 0, 0, 0, 0, 68, 0, 0, 0, 0, 0, 0, 0, 0, 0, 0, 0, 0, 0, 0, 0, 68, 0, 0, 0, 0, 0, 0, 0, 0, 0, 0, 0, 0, 0, 0, 0, 68, 0, 0, 0, 0, 0, 0, 0, 0, 0, 0, 0, 0, 0, 0, 68, 0, 0, 0, 0, 0, 0, 0, 0, 0, 0, 0, 0, 0, 0, 0, 68, 0, 0, 0, 0, 0, 0, 0, 0, 0, 0, 0, 0, 0, 0, 0, 68, 0, 0, 0, 0, 0, 0, 0, 0, 0, 0, 0, 0, 0, 0, 68, 0, 0, 0, 0, 0, 0, 0, 0, 0, 0, 0, 0, 0, 0, 0, 68, 0, 0, 0, 0, 0, 0, 0, 0, 0, 0, 0, 0, 0, 0, 0, 68, 0, 0, 0, 0, 0, 0, 0, 0, 0, 0, 0, 0, 0, 0, 0, 68, 0, 0, 0, 0, 0, 0, 0, 0, 0, 0, 0, 0, 0, 0, 0, 68, 0, 0, 0, 0, 0, 0, 0, 0, 0, 0, 0, 0, 0, 0, 0, 68, 0, 0, 0, 0, 0, 0, 0, 0, 0, 0, 0, 0, 0, 0, 0, 0, 68, 0, 0, 0, 0, 0, 0, 0, 0, 0, 0, 0, 0, 0, 0, 0, 68, 0, 0, 0, 0, 0, 0, 0, 0, 0, 0, 0, 0, 0, 0, 0, 68, 0, 0, 0, 0],
                 "height":16,
                 "width":16,
                 "x":-16,
                 "y":0
                }, 
                {
                 "data":[0, 0, 0, 0, 0, 0, 0, 0, 0, 0, 0, 0, 0, 0, 0, 0, 0, 0, 0, 0, 0, 0, 0, 0, 0, 0, 0, 0, 0, 0, 0, 0, 0, 0, 0, 0, 0, 0, 0, 0, 0, 0, 0, 0, 0, 0, 0, 0, 0, 0, 0, 0, 0, 0, 0, 0, 0, 0, 0, 0, 0, 0, 0, 0, 0, 0, 0, 0, 0, 0, 0, 0, 0, 0, 0, 0, 0, 0, 0, 0, 0, 0, 0, 0, 0, 0, 0, 0, 0, 0, 0, 0, 0, 0, 0, 0, 0, 0, 0, 0, 0, 0, 0, 0, 0, 0, 0, 0, 0, 0, 0, 0, 0, 0, 0, 0, 0, 0, 0, 0, 68, 68, 68, 68, 68, 68, 68, 0, 0, 0, 0, 0, 0, 0, 0, 0, 68, 0, 0, 0, 0, 0, 68, 0, 0, 0, 0, 0, 0, 0, 0, 0, 68, 0, 0, 0, 0, 0, 0, 0, 0, 0, 0, 0, 0, 0, 0, 0, 68, 0, 0, 0, 0, 0, 0, 0, 0, 0, 0, 0, 0, 0, 0, 0, 68, 0, 0, 0, 0, 0, 0, 0, 0, 0, 0, 0, 0, 0, 0, 0, 68, 0, 0, 0, 0, 0, 68, 0, 0, 0, 0, 0, 0, 0, 0, 0, 68, 68, 68, 68, 68, 68, 68, 0, 0, 0, 0, 0, 0, 0, 0, 0, 0, 0, 0, 0, 0, 0, 0, 0, 0, 0, 0, 0, 0, 0, 0, 0, 0, 0, 0, 0, 0, 0, 0, 0],
                 "height":16,
                 "width":16,
                 "x":0,
                 "y":0
                }, 
                {
                 "data":[0, 0, 0, 0, 0, 0, 68, 0, 0, 0, 0, 0, 0, 0, 0, 0, 0, 0, 0, 0, 0, 0, 0, 68, 0, 0, 0, 0, 0, 0, 0, 0, 0, 0, 0, 0, 0, 0, 0, 68, 0, 0, 0, 0, 0, 0, 0, 0, 0, 0, 0, 0, 0, 0, 0, 68, 0, 0, 0, 0, 0, 0, 0, 0, 0, 0, 0, 0, 0, 0, 0, 0, 68, 0, 0, 0, 0, 0, 0, 0, 0, 0, 0, 0, 0, 0, 0, 0, 68, 0, 0, 0, 0, 0, 0, 0, 0, 0, 0, 0, 0, 0, 0, 0, 68, 0, 0, 0, 0, 0, 0, 0, 0, 0, 0, 0, 0, 0, 0, 0, 0, 68, 0, 0, 0, 0, 0, 0, 0, 0, 0, 0, 0, 0, 0, 0, 0, 68, 0, 0, 0, 0, 0, 0, 0, 0, 0, 0, 0, 0, 0, 0, 0, 68, 0, 0, 0, 0, 0, 0, 0, 0, 0, 0, 0, 0, 0, 0, 0, 68, 0, 0, 0, 0, 0, 0, 0, 0, 0, 0, 0, 0, 0, 0, 0, 68, 0, 0, 0, 0, 0, 0, 0, 0, 0, 0, 0, 0, 0, 0, 0, 68, 0, 0, 0, 0, 0, 0, 0, 0, 0, 0, 0, 0, 0, 0, 68, 0, 0, 0, 0, 0, 0, 0, 0, 0, 0, 0, 0, 0, 0, 0, 68, 0, 0, 0, 0, 0, 0, 0, 0, 0, 0, 0, 0, 0, 0, 0, 68, 0, 0, 0, 0, 0, 0, 0],
                 "height":16,
                 "width":16,
                 "x":16,
                 "y":0
                }, 
                {
                 "data":[0, 0, 0, 0, 0, 0, 0, 0, 0, 0, 0, 0, 68, 0, 0, 0, 0, 0, 0, 0, 0, 0, 0, 0, 0, 0, 0, 0, 68, 0, 0, 0, 0, 0, 0, 0, 0, 0, 0, 0, 0, 0, 0, 0, 68, 0, 0, 0, 0, 0, 0, 0, 0, 0, 0, 0, 0, 0, 0, 0, 0, 68, 0, 0, 0, 0, 0, 0, 0, 0, 0, 0, 0, 0, 0, 0, 0, 68, 0, 0, 0, 0, 0, 0, 0, 0, 0, 0, 0, 0, 0, 0, 0, 0, 68, 0, 0, 0, 0, 0, 0, 0, 0, 0, 0, 0, 0, 0, 0, 0, 0, 68, 0, 0, 0, 0, 0, 0, 0, 0, 0, 0, 0, 0, 0, 0, 0, 0, 0, 0, 0, 0, 0, 0, 0, 0, 0, 0, 0, 0, 0, 0, 0, 0, 0, 0, 0, 0, 0, 0, 0, 0, 0, 0, 0, 0, 0, 0, 0, 0, 0, 0, 0, 0, 0, 0, 0, 0, 0, 0, 0, 0, 0, 0, 0, 0, 0, 0, 0, 0, 0, 0, 0, 0, 0, 0, 0, 0, 0, 0, 0, 0, 0, 0, 0, 0, 0, 0, 0, 0, 0, 0, 0, 0, 0, 0, 0, 0, 0, 0, 0, 0, 0, 0, 0, 0, 0, 0, 0, 0, 0, 0, 0, 0, 0, 0, 0, 0, 0, 0, 0, 0, 0, 0, 0, 0, 0, 0, 0, 0, 0, 0, 0, 0, 0, 0, 0, 0, 0, 0, 0, 0, 0, 0, 0, 0],
                 "height":16,
                 "width":16,
                 "x":-16,
                 "y":16
                }, 
                {
                 "data":[0, 0, 0, 0, 0, 0, 0, 0, 0, 0, 0, 0, 0, 0, 0, 0, 0, 0, 0, 0, 0, 0, 0, 0, 0, 0, 0, 0, 0, 0, 0, 0, 0, 0, 0, 0, 0, 0, 0, 0, 0, 0, 0, 0, 0, 0, 0, 0, 0, 0, 0, 0, 0, 0, 0, 0, 0, 0, 0, 0, 0, 0, 0, 0, 0, 0, 0, 0, 0, 0, 0, 0, 0, 0, 0, 0, 0, 0, 0, 0, 0, 0, 0, 0, 0, 0, 0, 0, 0, 0, 0, 0, 0, 0, 0, 0, 68, 0, 0, 0, 0, 0, 0, 0, 0, 0, 0, 0, 0, 0, 0, 0, 0, 68, 68, 68, 0, 0, 0, 0, 0, 0, 0, 0, 0, 0, 0, 0, 0, 0, 0, 0, 68, 68, 68, 0, 0, 0, 0, 0, 0, 68, 68, 68, 0, 0, 0, 0, 0, 0, 0, 68, 68, 68, 68, 68, 68, 0, 0, 0, 0, 0, 0, 0, 0, 0, 0, 0, 0, 0, 0, 0, 0, 0, 0, 0, 0, 0, 0, 0, 0, 0, 0, 0, 0, 0, 0, 0, 0, 0, 0, 0, 0, 0, 0, 0, 0, 0, 0, 0, 0, 0, 0, 0, 0, 0, 0, 0, 0, 0, 0, 0, 0, 0, 0, 0, 0, 0, 0, 0, 0, 0, 0, 0, 0, 0, 0, 0, 0, 0, 0, 0, 0, 0, 0, 0, 0, 0, 0, 0, 0, 0, 0, 0, 0, 0, 0, 0, 0, 0, 0, 0, 0, 0, 0, 0],
                 "height":16,
                 "width":16,
                 "x":0,
                 "y":16
                }, 
                {
                 "data":[0, 0, 0, 0, 0, 0, 0, 68, 0, 0, 0, 0, 0, 0, 0, 0, 0, 0, 0, 0, 0, 0, 0, 68, 0, 0, 0, 0, 0, 0, 0, 0, 0, 0, 0, 0, 0, 0, 0, 68, 0, 0, 0, 0, 0, 0, 0, 0, 0, 0, 0, 0, 0, 0, 68, 0, 0, 0, 0, 0, 0, 0, 0, 0, 0, 0, 0, 0, 0, 0, 68, 0, 0, 0, 0, 0, 0, 0, 0, 0, 0, 0, 0, 0, 0, 68, 0, 0, 0, 0, 0, 0, 0, 0, 0, 0, 0, 0, 0, 68, 68, 0, 0, 0, 0, 0, 0, 0, 0, 0, 0, 0, 68, 68, 68, 0, 0, 0, 0, 0, 0, 0, 0, 0, 0, 0, 0, 0, 0, 0, 0, 0, 0, 0, 0, 0, 0, 0, 0, 0, 0, 0, 0, 0, 0, 0, 0, 0, 0, 0, 0, 0, 0, 0, 0, 0, 0, 0, 0, 0, 0, 0, 0, 0, 0, 0, 0, 0, 0, 0, 0, 0, 0, 0, 0, 0, 0, 0, 0, 0, 0, 0, 0, 0, 0, 0, 0, 0, 0, 0, 0, 0, 0, 0, 0, 0, 0, 0, 0, 0, 0, 0, 0, 0, 0, 0, 0, 0, 0, 0, 0, 0, 0, 0, 0, 0, 0, 0, 0, 0, 0, 0, 0, 0, 0, 0, 0, 0, 0, 0, 0, 0, 0, 0, 0, 0, 0, 0, 0, 0, 0, 0, 0, 0, 0, 0, 0, 0, 0, 0, 0, 0, 0, 0, 0, 0],
                 "height":16,
                 "width":16,
                 "x":16,
                 "y":16
                }],
         "height":48,
         "id":7,
         "name":"collides",
         "opacity":1,
         "startx":-16,
         "starty":-16,
         "type":"tilelayer",
         "visible":true,
         "width":48,
         "x":0,
         "y":0
        }, 
        {
         "chunks":[
                {
                 "data":[0, 0, 0, 0, 0, 0, 0, 0, 0, 0, 0, 0, 0, 0, 0, 0, 0, 0, 0, 0, 0, 0, 0, 0, 0, 0, 0, 0, 0, 0, 0, 0, 0, 0, 0, 0, 0, 0, 0, 0, 0, 0, 0, 0, 0, 0, 0, 0, 0, 0, 0, 0, 0, 0, 0, 0, 0, 0, 0, 0, 0, 0, 0, 0, 0, 0, 0, 0, 0, 0, 0, 0, 0, 0, 0, 0, 0, 0, 0, 0, 0, 0, 0, 0, 0, 0, 0, 0, 0, 0, 0, 0, 0, 0, 0, 0, 0, 0, 0, 0, 0, 0, 0, 29, 29, 29, 29, 29, 29, 29, 29, 0, 0, 0, 0, 0, 0, 0, 0, 29, 29, 29, 29, 29, 29, 29, 29, 0, 0, 0, 0, 0, 0, 0, 0, 29, 29, 29, 29, 29, 29, 29, 29, 0, 0, 0, 0, 0, 0, 0, 0, 29, 29, 29, 29, 29, 29, 29, 29, 0, 0, 0, 0, 0, 0, 0, 0, 29, 29, 29, 29, 29, 29, 29, 29, 0, 0, 0, 0, 0, 0, 0, 0, 29, 29, 29, 29, 29, 29, 29, 29, 0, 0, 0, 0, 0, 0, 0, 0, 29, 29, 29, 29, 29, 29, 29, 29, 0, 0, 0, 0, 0, 0, 0, 0, 29, 29, 29, 29, 29, 29, 29, 29, 0, 0, 0, 0, 0, 0, 0, 0, 29, 29, 29, 29, 29, 29, 29, 29, 0, 0, 0, 0, 0, 0, 0, 0, 0, 0, 0, 0, 0, 0, 0, 0, 0],
                 "height":16,
                 "width":16,
                 "x":0,
                 "y":0
                }],
         "height":16,
         "id":17,
         "name":"treppenhaus4",
         "opacity":1,
         "startx":0,
         "starty":0,
         "type":"tilelayer",
         "visible":true,
         "width":16,
         "x":0,
         "y":0
        }, 
        {
         "chunks":[
                {
                 "data":[0, 0, 0, 0, 0, 0, 0, 0, 0, 0, 0, 0, 0, 0, 0, 0, 0, 0, 0, 0, 0, 0, 0, 0, 0, 0, 0, 0, 0, 0, 0, 0, 0, 0, 0, 0, 0, 0, 0, 0, 0, 0, 0, 0, 0, 0, 0, 0, 0, 0, 0, 0, 0, 0, 0, 0, 0, 0, 0, 0, 0, 0, 0, 0, 0, 0, 0, 0, 0, 0, 0, 0, 0, 0, 0, 0, 0, 0, 0, 0, 0, 0, 0, 0, 0, 0, 0, 0, 0, 0, 0, 0, 0, 0, 0, 0, 0, 0, 0, 0, 0, 0, 0, 0, 0, 0, 0, 0, 0, 0, 0, 0, 0, 0, 0, 0, 0, 0, 0, 0, 0, 0, 0, 0, 0, 0, 0, 0, 0, 0, 0, 0, 0, 0, 0, 0, 0, 0, 0, 0, 27, 27, 0, 0, 0, 0, 0, 0, 0, 0, 0, 0, 0, 0, 0, 0, 27, 27, 0, 0, 0, 0, 0, 0, 0, 0, 0, 0, 0, 0, 0, 160, 27, 0, 0, 0, 0, 0, 0, 0, 0, 0, 0, 0, 0, 0, 0, 0, 0, 0, 0, 0, 0, 0, 0, 0, 0, 0, 0, 0, 0, 0, 0, 0, 0, 27, 0, 0, 0, 0, 0, 0, 0, 0, 0, 0, 0, 0, 0, 0, 0, 0, 0, 0, 0, 0, 0, 0, 0, 0, 0, 0, 0, 0, 0, 0, 0, 0, 0, 0, 0, 0, 0, 0, 0, 0, 0, 0, 0, 0, 0, 0, 0, 0, 0, 0],
                 "height":16,
                 "width":16,
                 "x":0,
                 "y":0
                }],
         "height":16,
         "id":16,
         "name":"treppenhaus3",
         "opacity":1,
         "startx":0,
         "starty":0,
         "type":"tilelayer",
         "visible":true,
         "width":16,
         "x":0,
         "y":0
        }, 
        {
         "chunks":[
                {
                 "data":[0, 0, 0, 0, 0, 0, 0, 0, 0, 0, 0, 0, 0, 0, 0, 0, 0, 0, 0, 0, 0, 0, 0, 0, 0, 0, 0, 0, 0, 0, 0, 0, 0, 0, 0, 0, 0, 0, 0, 0, 0, 0, 0, 0, 0, 0, 0, 0, 0, 0, 0, 0, 0, 0, 0, 0, 0, 0, 0, 0, 0, 0, 0, 0, 0, 0, 0, 0, 0, 0, 0, 0, 0, 0, 0, 0, 0, 0, 0, 0, 0, 0, 0, 0, 0, 0, 0, 0, 0, 0, 0, 0, 0, 0, 0, 0, 0, 0, 0, 0, 0, 0, 0, 0, 0, 0, 0, 0, 0, 0, 0, 0, 0, 0, 0, 0, 0, 0, 0, 0, 0, 0, 0, 0, 0, 0, 0, 0, 0, 0, 0, 0, 0, 0, 0, 0, 0, 160, 160, 127, 0, 0, 0, 0, 0, 0, 0, 0, 0, 0, 0, 0, 1073742015, 175, 160, 160, 0, 2147483775, 0, 0, 0, 0, 0, 0, 0, 0, 0, 0, 1073742015, 1073742016, 175, 128, 2147483775, 2147483808, 0, 0, 0, 0, 0, 0, 0, 0, 0, 0, 1073742015, 1073742016, 0, 2147483775, 2147483808, 2147483808, 0, 0, 0, 0, 0, 0, 0, 0, 0, 0, 1073742015, 1073742016, 2147483775, 2147483808, 2147483808, 2147483823, 0, 0, 0, 0, 0, 0, 0, 0, 0, 0, 0, 2147483775, 2147483808, 2147483808, 2147483823, 0, 0, 0, 0, 0, 0, 0, 0, 0, 0, 0, 0, 0, 0, 0, 0, 0, 0, 0, 0, 0, 0, 0, 0, 0, 0, 0, 0, 0, 0, 0, 0, 0, 0, 0],
                 "height":16,
                 "width":16,
                 "x":0,
                 "y":0
                }],
         "height":16,
         "id":9,
         "name":"treppenhaus2",
         "opacity":1,
         "startx":0,
         "starty":0,
         "type":"tilelayer",
         "visible":true,
         "width":16,
         "x":0,
         "y":0
        }, 
        {
         "chunks":[
                {
                 "data":[0, 0, 0, 0, 0, 0, 0, 0, 0, 0, 0, 0, 0, 0, 0, 0, 0, 0, 0, 0, 0, 0, 0, 0, 0, 0, 0, 0, 0, 0, 0, 0, 0, 0, 0, 0, 0, 0, 0, 0, 0, 0, 0, 0, 0, 0, 0, 0, 0, 0, 0, 0, 0, 0, 0, 0, 0, 0, 0, 0, 0, 0, 0, 0, 0, 0, 0, 0, 0, 0, 0, 0, 0, 0, 0, 0, 0, 0, 0, 0, 0, 0, 0, 0, 0, 0, 0, 0, 0, 0, 0, 0, 0, 0, 0, 0, 0, 0, 0, 0, 0, 0, 0, 0, 0, 0, 0, 0, 0, 0, 0, 0, 0, 0, 0, 0, 0, 0, 0, 0, 0, 0, 0, 0, 0, 0, 0, 0, 0, 0, 0, 0, 0, 0, 0, 0, 0, 128, 0, 0, 0, 143, 0, 0, 0, 0, 0, 0, 0, 0, 0, 0, 0, 0, 128, 0, 143, 0, 0, 0, 0, 0, 0, 0, 0, 0, 0, 0, 0, 0, 0, 143, 0, 0, 0, 0, 0, 0, 0, 0, 0, 0, 0, 0, 0, 0, 143, 0, 0, 143, 0, 0, 0, 0, 0, 0, 0, 0, 0, 0, 0, 143, 0, 0, 143, 0, 0, 0, 0, 0, 0, 0, 0, 0, 0, 0, 0, 0, 0, 0, 0, 0, 0, 0, 0, 0, 0, 0, 0, 0, 0, 0, 0, 0, 0, 0, 0, 0, 0, 0, 0, 0, 0, 0, 0, 0, 0, 0, 0, 0, 0, 0, 0, 0, 0, 0],
                 "height":16,
                 "width":16,
                 "x":0,
                 "y":0
                }],
         "height":16,
         "id":10,
         "name":"treppenhaus1",
         "opacity":1,
         "startx":0,
         "starty":0,
         "type":"tilelayer",
         "visible":true,
         "width":16,
         "x":0,
         "y":0
        }, 
        {
         "chunks":[
                {
                 "data":[0, 0, 0, 0, 0, 0, 0, 0, 0, 0, 0, 0, 0, 0, 0, 0, 0, 0, 0, 0, 0, 0, 0, 0, 0, 0, 0, 0, 0, 0, 0, 0, 0, 0, 0, 0, 0, 0, 0, 0, 0, 0, 0, 0, 0, 0, 0, 0, 0, 0, 0, 0, 0, 0, 0, 0, 0, 0, 0, 0, 0, 0, 0, 0, 0, 0, 0, 0, 0, 0, 0, 0, 0, 0, 0, 0, 0, 0, 0, 0, 0, 0, 0, 0, 0, 0, 0, 0, 0, 0, 0, 0, 0, 0, 0, 0, 0, 0, 0, 0, 0, 0, 0, 0, 0, 0, 0, 0, 0, 0, 0, 0, 0, 0, 0, 0, 0, 0, 0, 0, 0, 0, 0, 0, 0, 0, 0, 0, 0, 0, 0, 0, 0, 0, 0, 0, 0, 0, 0, 0, 0, 0, 0, 0, 0, 0, 0, 0, 0, 0, 0, 0, 0, 0, 0, 0, 0, 0, 0, 0, 0, 0, 0, 0, 0, 0, 0, 0, 0, 0, 0, 0, 0, 0, 0, 0, 0, 0, 0, 0, 0, 0, 0, 0, 0, 0, 0, 0, 0, 0, 0, 0, 0, 0, 0, 0, 0, 0, 0, 0, 0, 0, 0, 0, 0, 0, 0, 0, 0, 0, 0, 0, 0, 0, 0, 0, 0, 0, 0, 0, 0, 0, 38, 38, 0, 0, 0, 0, 0, 0, 0, 0, 0, 0, 0, 0, 0, 38, 38, 28, 0, 0, 0, 0, 0, 0, 0, 0, 0, 0, 0, 0, 0, 38, 28, 28],
                 "height":16,
                 "width":16,
                 "x":-16,
                 "y":-16
                }, 
                {
                 "data":[0, 0, 0, 0, 0, 0, 0, 0, 0, 0, 0, 0, 0, 0, 0, 0, 0, 0, 0, 0, 0, 0, 0, 0, 0, 0, 0, 0, 0, 0, 0, 0, 0, 0, 0, 0, 0, 0, 0, 0, 0, 0, 0, 0, 0, 0, 0, 0, 0, 0, 0, 0, 0, 0, 0, 0, 0, 0, 0, 0, 0, 0, 0, 0, 0, 0, 0, 0, 0, 0, 0, 0, 0, 0, 0, 0, 0, 0, 0, 0, 0, 0, 0, 0, 0, 0, 0, 0, 0, 0, 0, 0, 0, 0, 0, 0, 0, 0, 0, 0, 0, 0, 0, 0, 0, 0, 0, 0, 0, 0, 0, 0, 0, 0, 0, 0, 0, 0, 0, 0, 0, 0, 0, 0, 0, 0, 0, 0, 0, 0, 0, 0, 0, 0, 0, 0, 0, 0, 0, 0, 0, 0, 0, 0, 0, 0, 0, 0, 0, 0, 38, 38, 38, 38, 38, 38, 38, 38, 0, 0, 0, 0, 0, 0, 38, 38, 38, 38, 38, 38, 38, 38, 38, 38, 38, 38, 0, 0, 38, 38, 38, 38, 38, 28, 28, 28, 28, 28, 28, 38, 38, 38, 38, 38, 38, 38, 28, 28, 28, 28, 28, 28, 28, 28, 28, 28, 28, 28, 38, 28, 28, 28, 28, 28, 28, 28, 28, 28, 28, 28, 28, 28, 28, 28, 28, 28, 28, 28, 28, 28, 28, 28, 28, 28, 28, 28, 28, 28, 28, 28, 28, 28, 28, 28, 28, 28, 28, 28, 28, 28, 28, 28, 28, 28, 28, 28],
                 "height":16,
                 "width":16,
                 "x":0,
                 "y":-16
                }, 
                {
                 "data":[0, 0, 0, 0, 0, 0, 0, 0, 0, 0, 0, 0, 0, 0, 0, 0, 0, 0, 0, 0, 0, 0, 0, 0, 0, 0, 0, 0, 0, 0, 0, 0, 0, 0, 0, 0, 0, 0, 0, 0, 0, 0, 0, 0, 0, 0, 0, 0, 0, 0, 0, 0, 0, 0, 0, 0, 0, 0, 0, 0, 0, 0, 0, 0, 0, 0, 0, 0, 0, 0, 0, 0, 0, 0, 0, 0, 0, 0, 0, 0, 0, 0, 0, 0, 0, 0, 0, 0, 0, 0, 0, 0, 0, 0, 0, 0, 0, 0, 0, 0, 0, 0, 0, 0, 0, 0, 0, 0, 0, 0, 0, 0, 0, 0, 0, 0, 0, 0, 0, 0, 0, 0, 0, 0, 0, 0, 0, 0, 0, 0, 0, 0, 0, 0, 0, 0, 0, 0, 0, 0, 0, 0, 0, 0, 0, 0, 0, 0, 0, 0, 0, 0, 0, 0, 0, 0, 0, 0, 0, 0, 0, 0, 0, 0, 0, 0, 0, 0, 0, 0, 0, 0, 0, 0, 0, 0, 38, 38, 0, 0, 0, 0, 0, 0, 0, 0, 0, 0, 0, 0, 0, 0, 38, 38, 38, 38, 0, 0, 0, 0, 0, 0, 0, 0, 0, 0, 0, 0, 28, 28, 28, 38, 38, 38, 0, 0, 0, 0, 0, 0, 0, 0, 0, 0, 28, 28, 28, 28, 28, 38, 38, 0, 0, 0, 0, 0, 0, 0, 0, 0, 28, 28, 28, 28, 28, 28, 38, 0, 0, 0, 0, 0, 0, 0, 0, 0],
                 "height":16,
                 "width":16,
                 "x":16,
                 "y":-16
                }, 
                {
                 "data":[0, 0, 0, 0, 0, 0, 0, 0, 0, 0, 0, 0, 38, 38, 28, 28, 0, 0, 0, 0, 0, 0, 0, 0, 0, 0, 0, 0, 38, 28, 28, 28, 0, 0, 0, 0, 0, 0, 0, 0, 0, 0, 0, 38, 38, 28, 28, 28, 0, 0, 0, 0, 0, 0, 0, 0, 0, 0, 0, 38, 38, 28, 28, 28, 0, 0, 0, 0, 0, 0, 0, 0, 0, 0, 38, 38, 28, 28, 28, 28, 0, 0, 0, 0, 0, 0, 0, 0, 0, 0, 38, 38, 28, 28, 28, 28, 0, 0, 0, 0, 0, 0, 0, 0, 0, 38, 38, 38, 28, 28, 28, 28, 0, 0, 0, 0, 0, 0, 0, 0, 0, 38, 38, 28, 28, 28, 28, 28, 0, 0, 0, 0, 0, 0, 0, 0, 0, 38, 38, 28, 28, 28, 28, 28, 0, 0, 0, 0, 0, 0, 0, 0, 0, 38, 38, 28, 28, 28, 28, 28, 0, 0, 0, 0, 0, 0, 0, 0, 0, 38, 38, 28, 28, 28, 28, 28, 0, 0, 0, 0, 0, 0, 0, 0, 0, 38, 38, 28, 28, 28, 28, 28, 0, 0, 0, 0, 0, 0, 0, 0, 0, 38, 38, 28, 28, 28, 28, 28, 0, 0, 0, 0, 0, 0, 0, 0, 0, 38, 38, 38, 28, 28, 28, 28, 0, 0, 0, 0, 0, 0, 0, 0, 0, 0, 38, 38, 28, 28, 28, 28, 0, 0, 0, 0, 0, 0, 0, 0, 0, 0, 38, 38, 28, 28, 28, 28],
                 "height":16,
                 "width":16,
                 "x":-16,
                 "y":0
                }, 
                {
                 "data":[28, 28, 28, 28, 28, 28, 28, 28, 28, 28, 28, 28, 28, 28, 28, 28, 28, 28, 28, 28, 28, 28, 28, 28, 28, 28, 28, 28, 28, 28, 28, 28, 28, 28, 28, 28, 28, 28, 28, 28, 28, 28, 28, 28, 28, 28, 28, 28, 28, 28, 28, 28, 28, 28, 28, 28, 28, 28, 28, 28, 28, 28, 28, 28, 28, 28, 28, 28, 28, 28, 28, 28, 28, 28, 28, 28, 28, 28, 28, 28, 28, 28, 28, 28, 28, 28, 28, 28, 28, 28, 28, 28, 28, 28, 28, 28, 28, 28, 28, 28, 28, 28, 28, 28, 28, 28, 28, 28, 28, 28, 28, 28, 28, 28, 28, 28, 28, 28, 28, 28, 28, 28, 28, 28, 28, 28, 28, 28, 28, 28, 28, 28, 28, 28, 28, 28, 28, 0, 0, 0, 0, 0, 28, 28, 28, 28, 28, 28, 28, 28, 28, 28, 28, 0, 0, 0, 0, 0, 28, 28, 28, 28, 28, 28, 28, 28, 28, 28, 28, 0, 0, 0, 0, 0, 28, 28, 28, 28, 28, 28, 28, 28, 28, 28, 28, 0, 0, 0, 0, 0, 28, 28, 28, 28, 28, 28, 28, 28, 28, 28, 28, 0, 0, 0, 0, 0, 28, 28, 28, 28, 28, 28, 28, 28, 28, 28, 28, 28, 28, 28, 28, 28, 28, 28, 28, 28, 28, 28, 28, 28, 28, 28, 28, 28, 28, 28, 28, 28, 28, 28, 28, 28, 28, 28, 28, 28, 28, 28, 28, 28, 28, 28, 28, 28, 28, 28],
                 "height":16,
                 "width":16,
                 "x":0,
                 "y":0
                }, 
                {
                 "data":[28, 28, 28, 28, 28, 28, 38, 38, 0, 0, 0, 0, 0, 0, 0, 0, 28, 28, 28, 28, 28, 28, 28, 38, 0, 0, 0, 0, 0, 0, 0, 0, 28, 28, 28, 28, 28, 28, 28, 38, 38, 0, 0, 0, 0, 0, 0, 0, 28, 28, 28, 28, 28, 28, 28, 38, 38, 0, 0, 0, 0, 0, 0, 0, 28, 28, 28, 28, 28, 28, 28, 28, 38, 38, 0, 0, 0, 0, 0, 0, 28, 28, 28, 28, 28, 28, 28, 28, 38, 38, 0, 0, 0, 0, 0, 0, 28, 28, 28, 28, 28, 28, 28, 28, 38, 38, 38, 0, 0, 0, 0, 0, 28, 28, 28, 28, 28, 28, 28, 28, 28, 38, 38, 0, 0, 0, 0, 0, 28, 28, 28, 28, 28, 28, 28, 28, 28, 38, 38, 0, 0, 0, 0, 0, 28, 28, 28, 28, 28, 28, 28, 28, 28, 38, 38, 0, 0, 0, 0, 0, 28, 28, 28, 28, 28, 28, 28, 28, 28, 38, 38, 0, 0, 0, 0, 0, 28, 28, 28, 28, 28, 28, 28, 28, 28, 38, 38, 0, 0, 0, 0, 0, 28, 28, 28, 28, 28, 28, 28, 28, 28, 38, 38, 0, 0, 0, 0, 0, 28, 28, 28, 28, 28, 28, 28, 28, 38, 38, 38, 0, 0, 0, 0, 0, 28, 28, 28, 28, 28, 28, 28, 28, 38, 38, 0, 0, 0, 0, 0, 0, 28, 28, 28, 28, 28, 28, 28, 28, 38, 38, 0, 0, 0, 0, 0, 0],
                 "height":16,
                 "width":16,
                 "x":16,
                 "y":0
                }, 
                {
                 "data":[0, 0, 0, 0, 0, 0, 0, 0, 0, 0, 0, 38, 38, 28, 28, 28, 0, 0, 0, 0, 0, 0, 0, 0, 0, 0, 0, 38, 38, 28, 28, 28, 0, 0, 0, 0, 0, 0, 0, 0, 0, 0, 0, 0, 38, 28, 28, 28, 0, 0, 0, 0, 0, 0, 0, 0, 0, 0, 0, 0, 38, 38, 28, 28, 0, 0, 0, 0, 0, 0, 0, 0, 0, 0, 0, 0, 0, 38, 28, 28, 0, 0, 0, 0, 0, 0, 0, 0, 0, 0, 0, 0, 0, 38, 38, 28, 0, 0, 0, 0, 0, 0, 0, 0, 0, 0, 0, 0, 0, 0, 38, 38, 0, 0, 0, 0, 0, 0, 0, 0, 0, 0, 0, 0, 0, 0, 0, 0, 0, 0, 0, 0, 0, 0, 0, 0, 0, 0, 0, 0, 0, 0, 0, 0, 0, 0, 0, 0, 0, 0, 0, 0, 0, 0, 0, 0, 0, 0, 0, 0, 0, 0, 0, 0, 0, 0, 0, 0, 0, 0, 0, 0, 0, 0, 0, 0, 0, 0, 0, 0, 0, 0, 0, 0, 0, 0, 0, 0, 0, 0, 0, 0, 0, 0, 0, 0, 0, 0, 0, 0, 0, 0, 0, 0, 0, 0, 0, 0, 0, 0, 0, 0, 0, 0, 0, 0, 0, 0, 0, 0, 0, 0, 0, 0, 0, 0, 0, 0, 0, 0, 0, 0, 0, 0, 0, 0, 0, 0, 0, 0, 0, 0, 0, 0, 0, 0, 0, 0, 0, 0, 0, 0, 0, 0, 0, 0],
                 "height":16,
                 "width":16,
                 "x":-16,
                 "y":16
                }, 
                {
                 "data":[28, 28, 28, 28, 28, 28, 28, 28, 28, 28, 28, 28, 28, 28, 28, 28, 28, 28, 28, 28, 28, 28, 28, 28, 28, 28, 28, 28, 28, 28, 28, 28, 28, 28, 28, 28, 28, 28, 28, 28, 28, 28, 28, 28, 28, 28, 28, 28, 28, 28, 28, 28, 28, 28, 28, 28, 28, 28, 28, 28, 28, 28, 28, 28, 28, 28, 28, 28, 28, 28, 28, 28, 28, 28, 28, 28, 28, 28, 28, 28, 28, 28, 28, 28, 28, 28, 28, 28, 28, 28, 28, 28, 28, 28, 28, 28, 38, 28, 28, 28, 28, 28, 28, 28, 28, 28, 28, 28, 28, 28, 28, 28, 38, 38, 38, 38, 28, 28, 28, 28, 28, 28, 28, 28, 28, 28, 28, 28, 0, 0, 38, 38, 38, 38, 38, 28, 28, 28, 28, 28, 28, 38, 38, 38, 0, 0, 0, 0, 38, 38, 38, 38, 38, 38, 38, 38, 38, 38, 38, 38, 0, 0, 0, 0, 0, 0, 38, 38, 38, 38, 38, 38, 38, 38, 0, 0, 0, 0, 0, 0, 0, 0, 0, 0, 0, 0, 0, 0, 0, 0, 0, 0, 0, 0, 0, 0, 0, 0, 0, 0, 0, 0, 0, 0, 0, 0, 0, 0, 0, 0, 0, 0, 0, 0, 0, 0, 0, 0, 0, 0, 0, 0, 0, 0, 0, 0, 0, 0, 0, 0, 0, 0, 0, 0, 0, 0, 0, 0, 0, 0, 0, 0, 0, 0, 0, 0, 0, 0, 0, 0, 0, 0, 0, 0, 0, 0],
                 "height":16,
                 "width":16,
                 "x":0,
                 "y":16
                }, 
                {
                 "data":[28, 28, 28, 28, 28, 28, 28, 38, 38, 0, 0, 0, 0, 0, 0, 0, 28, 28, 28, 28, 28, 28, 28, 38, 38, 0, 0, 0, 0, 0, 0, 0, 28, 28, 28, 28, 28, 28, 28, 38, 0, 0, 0, 0, 0, 0, 0, 0, 28, 28, 28, 28, 28, 28, 38, 38, 0, 0, 0, 0, 0, 0, 0, 0, 28, 28, 28, 28, 28, 28, 38, 0, 0, 0, 0, 0, 0, 0, 0, 0, 28, 28, 28, 28, 28, 38, 38, 0, 0, 0, 0, 0, 0, 0, 0, 0, 28, 28, 28, 38, 38, 38, 0, 0, 0, 0, 0, 0, 0, 0, 0, 0, 38, 38, 38, 38, 0, 0, 0, 0, 0, 0, 0, 0, 0, 0, 0, 0, 38, 38, 0, 0, 0, 0, 0, 0, 0, 0, 0, 0, 0, 0, 0, 0, 0, 0, 0, 0, 0, 0, 0, 0, 0, 0, 0, 0, 0, 0, 0, 0, 0, 0, 0, 0, 0, 0, 0, 0, 0, 0, 0, 0, 0, 0, 0, 0, 0, 0, 0, 0, 0, 0, 0, 0, 0, 0, 0, 0, 0, 0, 0, 0, 0, 0, 0, 0, 0, 0, 0, 0, 0, 0, 0, 0, 0, 0, 0, 0, 0, 0, 0, 0, 0, 0, 0, 0, 0, 0, 0, 0, 0, 0, 0, 0, 0, 0, 0, 0, 0, 0, 0, 0, 0, 0, 0, 0, 0, 0, 0, 0, 0, 0, 0, 0, 0, 0, 0, 0, 0, 0, 0, 0, 0, 0, 0, 0],
                 "height":16,
                 "width":16,
                 "x":16,
                 "y":16
                }],
         "height":48,
         "id":8,
         "name":"bottom",
         "opacity":1,
         "startx":-16,
         "starty":-16,
         "type":"tilelayer",
         "visible":true,
         "width":48,
         "x":0,
         "y":0
        }, 
        {
         "chunks":[
                {
                 "data":[0, 0, 0, 0, 0, 0, 0, 0, 0, 0, 0, 0, 0, 0, 0, 0, 0, 0, 0, 0, 0, 0, 0, 0, 0, 0, 0, 0, 0, 0, 0, 0, 0, 0, 0, 0, 0, 0, 0, 0, 0, 0, 0, 0, 0, 0, 0, 0, 0, 0, 0, 0, 0, 0, 0, 0, 0, 0, 0, 0, 0, 0, 0, 0, 0, 0, 0, 0, 0, 0, 0, 0, 0, 0, 0, 0, 0, 0, 0, 0, 0, 0, 0, 0, 0, 0, 0, 0, 0, 0, 0, 0, 0, 0, 0, 0, 0, 0, 0, 0, 0, 0, 0, 0, 0, 0, 0, 0, 0, 0, 0, 0, 0, 0, 0, 0, 0, 0, 0, 0, 291, 325, 325, 325, 325, 325, 294, 0, 0, 0, 0, 0, 0, 0, 0, 0, 310, 0, 0, 0, 0, 0, 0, 0, 0, 0, 0, 0, 0, 0, 0, 0, 310, 0, 0, 0, 0, 0, 0, 0, 0, 0, 0, 0, 0, 0, 0, 0, 310, 0, 0, 0, 0, 0, 0, 0, 0, 0, 0, 0, 0, 0, 0, 0, 310, 0, 0, 0, 0, 0, 0, 0, 0, 0, 0, 0, 0, 0, 0, 0, 310, 0, 0, 0, 0, 0, 310, 0, 0, 0, 0, 0, 0, 0, 0, 0, 323, 325, 325, 325, 325, 325, 326, 0, 0, 0, 0, 0, 0, 0, 0, 0, 0, 0, 0, 0, 0, 0, 0, 0, 0, 0, 0, 0, 0, 0, 0, 0, 0, 0, 0, 0, 0, 0, 0, 0],
                 "height":16,
                 "width":16,
                 "x":0,
                 "y":0
                }],
         "height":16,
         "id":14,
         "name":"top",
         "opacity":1,
         "startx":0,
         "starty":0,
         "type":"tilelayer",
         "visible":true,
         "width":16,
         "x":0,
         "y":0
        }, 
        {
         "chunks":[],
         "height":0,
         "id":15,
         "name":"book",
         "opacity":1,
         "startx":0,
         "starty":0,
         "type":"tilelayer",
         "visible":true,
         "width":0,
         "x":0,
         "y":0
        }, 
        {
         "draworder":"topdown",
         "id":6,
         "name":"floorLayer",
         "objects":[],
         "opacity":1,
         "type":"objectgroup",
         "visible":true,
         "x":0,
         "y":0
        }, 
        {
         "chunks":[],
         "height":0,
         "id":11,
         "name":"drueber",
         "opacity":1,
         "startx":0,
         "starty":0,
         "type":"tilelayer",
         "visible":true,
         "width":0,
         "x":0,
         "y":0
        }],
 "nextlayerid":18,
 "nextobjectid":1,
 "orientation":"orthogonal",
 "renderorder":"right-down",
 "tiledversion":"1.4.3",
 "tileheight":32,
 "tilesets":[
        {
         "columns":8,
         "firstgid":1,
         "image":"floortileset.png",
         "imageheight":256,
         "imagewidth":256,
         "margin":0,
         "name":"floortileset",
         "spacing":0,
         "tilecount":64,
         "tileheight":32,
         "tilewidth":32
        }, 
        {
         "columns":9,
         "firstgid":65,
         "image":"mapUtilities.png",
         "imageheight":32,
         "imagewidth":288,
         "margin":0,
         "name":"mapUtilities",
         "spacing":0,
         "tilecount":9,
         "tileheight":32,
         "tiles":[
                {
                 "id":3,
                 "properties":[
                        {
                         "name":"collides",
                         "type":"bool",
                         "value":true
                        }]
                }],
         "tilewidth":32
        }, 
        {
         "columns":16,
         "firstgid":74,
         "image":"tilesets_deviant_milkian_1.png",
         "imageheight":512,
         "imagewidth":512,
         "margin":0,
         "name":"tilesets_deviant_milkian_1",
         "spacing":0,
         "tilecount":256,
         "tileheight":32,
         "tilewidth":32
        }],
 "tilewidth":32,
 "type":"map",
 "version":1.4,
 "width":22
}